flask_visjs/__init__.py
flask_visjs/_version.py
flask_visjs/static/vis.min.css
flask_visjs/static/vis.min.js
flask_visjs/templates/pyvis.css.j2
flask_visjs/templates/pyvis.html.j2
flask_visjs/templates/pyvis.js.j2
Flask_VisJS-0.1.4.dist-info/LICENSE
Flask_VisJS-0.1.4.dist-info/METADATA
Flask_VisJS-0.1.4.dist-info/WHEEL
Flask_VisJS-0.1.4.dist-info/top_level.txt
Flask_VisJS-0.1.4.dist-info/RECORD
