Metadata-Version: 2.1
Name: Flask-VisJS
Version: 0.1.4
Summary: A simple flask wrapper for the famous visjs library.
Home-page: https://github.com/dadav/Flask-VisJS
Author: dadav
Author-email: dadav@protonmail.com
Maintainer: dadav
Maintainer-email: dadav@protonmail.com
License: BSD
Project-URL: Bug Tracker, https://github.com/dadav/Flask-VisJS/issues
Keywords: flask,visjs
Platform: any
Classifier: Environment :: Web Environment
Classifier: Intended Audience :: Developers
Classifier: License :: OSI Approved :: BSD License
Classifier: Operating System :: OS Independent
Classifier: Programming Language :: Python
Classifier: Topic :: Internet :: WWW/HTTP :: Dynamic Content
Classifier: Topic :: Software Development :: Libraries :: Python Modules
Requires-Python: >=3.6
License-File: LICENSE
Requires-Dist: Flask (<3)
Requires-Dist: pyvis
